pyconvertalert/__init__.py
pyconvertalert/__version__.py
pyconvertalert/py_convert_alert.py
pyconvertalert-0.1.1.dist-info/LICENSE
pyconvertalert-0.1.1.dist-info/METADATA
pyconvertalert-0.1.1.dist-info/WHEEL
pyconvertalert-0.1.1.dist-info/top_level.txt
pyconvertalert-0.1.1.dist-info/RECORD
