Metadata-Version: 2.1
Name: pyconvertalert
Version: 0.1.1
Summary: Convert arbitrary json alerts to Alert Manager alerts
Home-page: https://github.com/jpavlav/PyConvertAlert
Author: Justin Palmer
Author-email: jpavlav@gmail.com
License: MIT
Platform: UNKNOWN
Classifier: License :: OSI Approved :: MIT License
Classifier: Programming Language :: Python :: 3
Classifier: Programming Language :: Python :: 3.6
Classifier: Topic :: System :: Systems Administration
Classifier: Topic :: Software Development :: Libraries
Classifier: Topic :: Software Development :: Libraries :: Python Modules
Requires-Python: >=3.6.0
Requires-Dist: six (>=1.11.0)
Requires-Dist: nested-lookup (>=0.2.1)
